Tests/test_utils.py
desu/__init__.py
desu/core.py
desu/test.py
desu-0.1.5.dist-info/METADATA
desu-0.1.5.dist-info/WHEEL
desu-0.1.5.dist-info/top_level.txt
desu-0.1.5.dist-info/RECORD
