Metadata-Version: 2.4
Name: desu
Version: 0.1.5
Summary: Lightweight utilities for data science, data engineering, and data analysis projects.
Author-email: Misael García <misagtor@gmail.com>
License-Expression: MIT
Keywords: data,utilities,data-science,data-engineering,data-analysis
Classifier: Programming Language :: Python :: 3
Classifier: Operating System :: OS Independent
Requires-Python: >=3.8
Requires-Dist: pandas>=1.0.0
Requires-Dist: seaborn
Requires-Dist: matplotlib
